solarlog_ardexa.py
solarlog_ardexa-2.0.11.dist-info/METADATA
solarlog_ardexa-2.0.11.dist-info/RECORD
solarlog_ardexa-2.0.11.dist-info/WHEEL
solarlog_ardexa-2.0.11.dist-info/entry_points.txt
solarlog_ardexa-2.0.11.dist-info/top_level.txt
