Metadata-Version: 2.1
Name: solarlog-ardexa
Version: 2.0.11
Summary: Collect from Solar Log devices and send the data to your cloud using Ardexa
Home-page: https://github.com/ardexa/solar-log
Author: Ardexa Pty Limited
Author-email: support@ardexa.com
License: UNKNOWN
Project-URL: Bug Reports, https://github.com/ardexa/solar-log/issues
Project-URL: Source, https://github.com/ardexa/solar-log/
Keywords: solar log SolarLog inverter ardexa
Platform: UNKNOWN
Classifier: License :: OSI Approved :: MIT License
Classifier: Programming Language :: Python :: 2
Classifier: Programming Language :: Python :: 2.7
Classifier: Programming Language :: Python :: 3
Classifier: Programming Language :: Python :: 3.4
Classifier: Programming Language :: Python :: 3.5
Classifier: Programming Language :: Python :: 3.6
Requires-Python: >=2.7
Requires-Dist: future
Requires-Dist: ardexaplugin
Requires-Dist: Click
Requires-Dist: requests
Requires-Dist: python-dateutil
